dannymac180_meta_agent-0.1.0.dist-info/licenses/LICENSE
meta_agent/__init__.py
meta_agent/agent_generator.py
meta_agent/cli.py
dannymac180_meta_agent-0.1.0.dist-info/METADATA
dannymac180_meta_agent-0.1.0.dist-info/WHEEL
dannymac180_meta_agent-0.1.0.dist-info/entry_points.txt
dannymac180_meta_agent-0.1.0.dist-info/top_level.txt
dannymac180_meta_agent-0.1.0.dist-info/RECORD
