Metadata-Version: 2.4
Name: dannymac180-meta-agent
Version: 0.1.0
Summary: A meta agent that creates OpenAI Agents SDK agents
Author: Meta Agent Developer
License-Expression: MIT
Project-URL: Homepage, https://github.com/DannyMac180/meta-agent
Project-URL: Bug Tracker, https://github.com/DannyMac180/meta-agent/issues
Project-URL: Documentation, https://github.com/DannyMac180/meta-agent#readme
Project-URL: Source Code, https://github.com/DannyMac180/meta-agent
Classifier: Programming Language :: Python :: 3
Classifier: Programming Language :: Python :: 3.8
Classifier: Programming Language :: Python :: 3.9
Classifier: Programming Language :: Python :: 3.10
Classifier: Programming Language :: Python :: 3.11
Classifier: Operating System :: OS Independent
Classifier: Development Status :: 4 - Beta
Classifier: Intended Audience :: Developers
Classifier: Topic :: Software Development :: Libraries :: Python Modules
Classifier: Topic :: Scientific/Engineering :: Artificial Intelligence
Requires-Python: >=3.8
License-File: LICENSE
Requires-Dist: openai-agents
Requires-Dist: pydantic
Requires-Dist: asyncio
Requires-Dist: typing
Requires-Dist: python-dotenv
Requires-Dist: requests
Requires-Dist: beautifulsoup4
Dynamic: license-file
